pygifconvt_jw/__init__.py
pygifconvt_jw/converter.py
pygifconvt_jw-1.0.1.dist-info/LICENSE
pygifconvt_jw-1.0.1.dist-info/METADATA
pygifconvt_jw-1.0.1.dist-info/WHEEL
pygifconvt_jw-1.0.1.dist-info/top_level.txt
pygifconvt_jw-1.0.1.dist-info/RECORD
